LICENSE.md
README.md
setup.cfg
setup.py
krisinformation/__init__.py
krisinformation/crisis_alerter.py
krisinformation.egg-info/PKG-INFO
krisinformation.egg-info/SOURCES.txt
krisinformation.egg-info/dependency_links.txt
krisinformation.egg-info/top_level.txt